mai/__init__.py
mai/__main__.py
mai/cli.py
stups_mai-1.0.10.dist-info/DESCRIPTION.rst
stups_mai-1.0.10.dist-info/METADATA
stups_mai-1.0.10.dist-info/RECORD
stups_mai-1.0.10.dist-info/WHEEL
stups_mai-1.0.10.dist-info/entry_points.txt
stups_mai-1.0.10.dist-info/metadata.json
stups_mai-1.0.10.dist-info/top_level.txt
