Metadata-Version: 2.0
Name: stups-mai
Version: 1.0.10
Summary: AWS SAML login CLI
Home-page: https://github.com/zalando-stups/mai
Author: Henning Jacobs
Author-email: henning.jacobs@zalando.de
License: Apache License 2.0
Keywords: aws account saml login federated shibboleth
Platform: UNKNOWN
Classifier: Development Status :: 4 - Beta
Classifier: Environment :: Console
Classifier: Intended Audience :: Developers
Classifier: Intended Audience :: System Administrators
Classifier: License :: OSI Approved :: Apache Software License
Classifier: Operating System :: POSIX :: Linux
Classifier: Programming Language :: Python
Classifier: Programming Language :: Python :: 3.4
Classifier: Programming Language :: Python :: Implementation :: CPython
Requires-Dist: PyYAML
Requires-Dist: aws-saml-login (>=1.0.11)
Requires-Dist: clickclick (>=0.6)
Requires-Dist: cryptography (>=1.7.1)
Requires-Dist: keyring
Requires-Dist: keyrings.alt
